Hand_Gestures/HandTrackingModule.py
Hand_Gestures/__init__.py
Hand_Gestures-0.1.4.dist-info/LICENSE
Hand_Gestures-0.1.4.dist-info/METADATA
Hand_Gestures-0.1.4.dist-info/WHEEL
Hand_Gestures-0.1.4.dist-info/top_level.txt
Hand_Gestures-0.1.4.dist-info/RECORD
