Metadata-Version: 2.1
Name: Hand-Gestures
Version: 0.1.4
Summary: a minimalist custom module for mediapipe
Home-page: https://github.com/DILPREET1910/Hand-Gestures-module
Author: DILPREET1910
Author-email: dsahney1910@gmail.com
Project-URL: Bug Tracker, https://github.com/DILPREET1910/Hand-Gestures-module/issues
Classifier: Programming Language :: Python :: 3.10
Classifier: Operating System :: OS Independent
Requires-Python: >=3.6
License-File: LICENSE
